shittywebserver/__init__.py
shittywebserver/api.py
shittywebserver/config.py
shittywebserver/main.py
shittywebserver/test.py
shittywebserver/tools.py
shittywebserver-0.0.8.dist-info/METADATA
shittywebserver-0.0.8.dist-info/WHEEL
shittywebserver-0.0.8.dist-info/top_level.txt
shittywebserver-0.0.8.dist-info/RECORD
