Metadata-Version: 2.1
Name: shittywebserver
Version: 0.0.8
Summary: A tiny misbehaving web API server, for testing web consuming apps.
Home-page: https://git.connect.dzd-ev.de/dzdpythonmodules/shittywebserver
Author: TB
Author-email: tim.bleimehl@helmholtz-muenchen.de
License: MIT
Requires-Python: >=3.9
Requires-Dist: uvicorn[standard]
Requires-Dist: fastapi[all]
Requires-Dist: DZDConfigs
